walver_sdk/__init__.py
walver_sdk/async_client.py
walver_sdk/client.py
walver_sdk/models.py
walver_sdk/py.typed
walver_sdk-0.1.0.dist-info/licenses/LICENSE
walver_sdk-0.1.0.dist-info/METADATA
walver_sdk-0.1.0.dist-info/WHEEL
walver_sdk-0.1.0.dist-info/top_level.txt
walver_sdk-0.1.0.dist-info/RECORD
