Metadata-Version: 2.4
Name: walver-sdk
Version: 0.1.0
Summary: A comprehensive Python wrapper for the Walver API
Home-page: https://github.com/walver-io/walver-python-sdk
Author: BonifacioCalindoro
Author-email: admin@walver.io
Keywords: walver,api,wrapper,client,wallet,verificationblockchain,solana,ethereum,crypto,tokengate
Classifier: Development Status :: 3 - Alpha
Classifier: Intended Audience :: Developers
Classifier: License :: OSI Approved :: MIT License
Classifier: Programming Language :: Python :: 3
Classifier: Programming Language :: Python :: 3.7
Classifier: Programming Language :: Python :: 3.8
Classifier: Programming Language :: Python :: 3.9
Classifier: Programming Language :: Python :: 3.10
Classifier: Programming Language :: Python :: 3.11
Classifier: Programming Language :: Python :: 3.12
Classifier: Programming Language :: Python :: 3.13
Classifier: Operating System :: OS Independent
Classifier: Topic :: Software Development :: Libraries :: Python Modules
Classifier: Typing :: Typed
Requires-Python: >=3.7
License-File: LICENSE
Requires-Dist: anyio==4.9.0
Requires-Dist: certifi==2025.4.26
Requires-Dist: charset-normalizer==3.4.1
Requires-Dist: h11==0.16.0
Requires-Dist: httpcore==1.0.9
Requires-Dist: httpx==0.28.1
Requires-Dist: idna==3.10
Requires-Dist: python-dotenv==1.1.0
Requires-Dist: requests==2.32.3
Requires-Dist: sniffio==1.3.1
Requires-Dist: urllib3==2.4.0
Dynamic: author
Dynamic: author-email
Dynamic: classifier
Dynamic: description
Dynamic: description-content-type
Dynamic: home-page
Dynamic: keywords
Dynamic: license-file
Dynamic: requires-dist
Dynamic: requires-python
Dynamic: summary
